bottlereact
