Metadata-Version: 1.1
Name: bottle-react
Version: 16.2.1
Summary: A microframework for Bottle+React projects.
Home-page: https://github.com/keredson/bottle-react
Author: Derek Anderson
Author-email: public@kered.org
License: UNKNOWN
Platform: UNKNOWN
Classifier: Development Status :: 4 - Beta
Classifier: Intended Audience :: Developers
Classifier: License :: OSI Approved :: MIT License
Classifier: Operating System :: OS Independent
Classifier: Programming Language :: Python
Classifier: Programming Language :: Python :: 3
